{
    "item_id": "127389838859",
    "title": "ASR Outdoor TraversaLace 550 lb Paracord Glow in the Dark Survival Shoe Laces",
    "category_id": "169282",
    "category_path": "Clothing, Shoes & Accessories|Specialty|Clothing & Shoe Care|Shoe Care & Repair|Shoe Laces",
    "aspects": {
        "Country of Origin": "United States",
        "Brand": "ASR Outdoor",
        "Thickness": "0.03",
        "Size": "36\" (4-5 Eyelets)",
        "Color": "Glow",
        "MPN": "TVLACE550-GLW3",
        "California Prop 65 Warning": "WARNING: This product may contain chemicals known to the State of California to cause cancer, birth defects or other reproductive harm",
        "UPC": "060886533696"
    },
    "condition": "New with tags",
    "is_group": false,
    "variation_count": 0,
    "status": "OK"
}
