{
    "item_id": "365879832395",
    "title": "Network Cable Tester and Modular Crimping Tool for Electronics Repair",
    "category_id": "51169",
    "category_path": "Computers/Tablets & Networking|Computer Cables & Connectors|Cabling Tools",
    "aspects": {
        "Country of Origin": "China",
        "Brand": "Universal Tool",
        "MPN": "UNIVERSALTOOL-CABLETESTER-6006N",
        "Type": "Precision Tools",
        "California Prop 65 Warning": "WARNING: This product can expose you to chemicals including bisphenol_a_(bpa), which is known to the State of California to cause cancer, birth defects or other reproductive harm. For more information, go to: www.P65Warnings.ca.gov",
        "Color": "Multi",
        "Size": "Standard",
        "UPC": "060886898627"
    },
    "condition": "New",
    "is_group": false,
    "variation_count": 0,
    "status": "OK"
}
