{
    "item_id": "365880019097",
    "title": "Freesole Shoe and Boot Repair Adhesive",
    "category_id": "36120",
    "category_path": "Sporting Goods|Camping & Hiking|Tents & Canopies|Tent & Canopy Accessories",
    "aspects": {
        "Country of Origin": "United States",
        "Type": "Repair Kit",
        "Brand": "Gear Aid",
        "Color": "Clear",
        "Item Height": "8.000",
        "Item Length": "5.000",
        "Item Width": "1.000",
        "Item Weight": "0.1000",
        "MPN": "10410-552",
        "Size": "1oz",
        "UPC": "166747696583"
    },
    "condition": "New",
    "is_group": false,
    "variation_count": 0,
    "status": "OK"
}
