{
    "category_id": "26261",
    "aspect_count": 8,
    "aspects": [
        {
            "name": "Brand",
            "required": false,
            "mode": "FREE_TEXT",
            "data_type": "STRING",
            "cardinality": "SINGLE",
            "for_variations": false,
            "values": [
                "3M",
                "A&BC",
                "Aarco",
                "ABB",
                "Acopian",
                "Acorn",
                "Acrison",
                "Adaptec",
                "ADC",
                "Advance",
                "AEG",
                "Aero",
                "AeroMarine Products",
                "Aeroquip",
                "aFe Power",
                "Aftermarket",
                "Agastat",
                "Agilent",
                "AGS",
                "Aixtron",
                "Alco Controls",
                "Alemite",
                "Alfa International",
                "Alfa Laval",
                "Alinabal",
                "Allanson",
                "Allen-Bradley",
                "Alliance",
                "Allied",
                "Allis-Chalmers",
                "Allison",
                "Altech Corp.",
                "Altronix",
                "Amada",
                "Amatom",
                "AMCO",
                "Amerex",
                "American Standard",
                "AMETEK",
                "AMF",
                "AMFLO",
                "AMI",
                "AMP",
                "Amperex",
                "Amphenol",
                "Amprobe",
                "AMX",
                "Anchor",
                "Anderson",
                "Andrew",
                "Andrews",
                "Anritsu",
                "Ansell",
                "Antec",
                "APC",
                "Apollo",
                "Appleton",
                "Applied Materials",
                "Arbor",
                "ARBURG",
                "Armstrong",
                "Arnold",
                "ARO",
                "Arrow Hart",
                "Asahi",
                "ASCO",
                "ASEA",
                "Ashcroft",
                "ASK",
                "ASML",
                "AST",
                "Atdec",
                "Atheros",
                "Atlas",
                "Atlas Copco",
                "Atlas Sound",
                "Atrax",
                "Auburn",
                "Aurora",
                "AutomationDirect",
                "Avaya",
                "Avery",
                "Avocent",
                "Avon",
                "AXE",
                "B&K Precision",
                "Baker",
                "Baldor",
                "BALDWIN",
                "Balluff",
                "Bally",
                "Bando",
                "Banner",
                "Barber-Greene",
                "Barden",
                "Barksdale",
                "Barnes",
                "BASF",
                "Bauer",
                "BCA",
                "Becton Dickinson",
                "Bel-Art",
                "Belkin",
                "Belvedere",
                "Bemis",
                "Bendix",
                "Bentley",
                "Best",
                "BESTORQ",
                "Best-Rite",
                "Bianchi",
                "Bimba",
                "Black Box",
                "Blue Point",
                "BMW",
                "Boardwalk",
                "Bobcat",
                "Bobrick",
                "Bogen",
                "Bosch",
                "Bostitch",
                "Boston",
                "Bower",
                "BPI",
                "Brady",
                "Brainerd",
                "BRANSON",
                "Bren-Tronics",
                "Bridgeport",
                "Briggs",
                "Briggs & Stratton",
                "Brinks",
                "Broadcom",
                "Brocade",
                "Brother",
                "Browning",
                "Bryant",
                "Buffalo Tools",
                "Bulgin",
                "Bullard",
                "Bulldog",
                "BUNN",
                "B\u00fcrkert",
                "BURNDY",
                "Busch",
                "Bush",
                "Bussmann",
                "C&M Corporation",
                "CAMCO",
                "Campbell",
                "Campbell Hausfeld",
                "Carejoy",
                "CAREL",
                "Carhartt",
                "Carling Technologies",
                "Carlisle",
                "Carlo Gavazzi",
                "Carlton",
                "Carmex",
                "CARQUEST",
                "Carrier",
                "Carriff",
                "Carr Lane",
                "Cascade",
                "Case",
                "Casio",
                "CAT",
                "Cbf",
                "CDI",
                "Central",
                "Central Pneumatic",
                "CENTURY",
                "Cepheid",
                "Champion",
                "Charmilles",
                "Chemtronics",
                "Cherne",
                "Chesterton",
                "Chevrolet",
                "Chicago Rawhide",
                "Chief",
                "CINCINNATI",
                "CIRCA",
                "Cisco",
                "CKD",
                "CK Products",
                "Clarostat",
                "Cle-Line",
                "Cleveland",
                "Clippard",
                "Cobra",
                "Codman",
                "Cognex",
                "Coherent",
                "Coilhose Pneumatics",
                "Columbus McKinnon",
                "Comair Rotron",
                "Commonwealth",
                "CommScope",
                "Compucessory",
                "Congress",
                "Consolidated",
                "CONTEC",
                "CONTEMP",
                "Continental",
                "Control Techniques",
                "Cooper",
                "Cordova",
                "Cornell Dubilier",
                "Corning",
                "Cosel",
                "Coto",
                "Craftsman",
                "Cramer",
                "Crestron",
                "Crimson",
                "Crouse-Hinds",
                "Crouzet",
                "Crown",
                "CR Seal",
                "Crydom",
                "Cummins",
                "Curtis",
                "Cutler-Hammer",
                "Cypress",
                "DADCO",
                "Danfoss",
                "Datalogic",
                "Dayco",
                "Dayton",
                "Delco Remy",
                "Dell",
                "Delta",
                "Denon",
                "Desco",
                "DE-STA-CO",
                "Deublin",
                "DeVilbiss",
                "DEWALT",
                "Dexter",
                "Diamond",
                "Diamondback",
                "Digi",
                "Digital",
                "Dillon",
                "Dixell",
                "DKF",
                "DoALL",
                "Dodge",
                "Dolby",
                "Donaldson",
                "Dormont",
                "Dr\u00e4ger",
                "Dremel",
                "Drive",
                "Dukane",
                "Duplo",
                "DURABLE",
                "Durametallic",
                "Durco",
                "Dwyer",
                "Dymo",
                "Dynabrade",
                "Dynapar",
                "Dynisco",
                "Dyson",
                "Eagle",
                "Eagle Signal",
                "Eaton",
                "EBC",
                "ebm-papst",
                "Eclipse",
                "Edelmann",
                "Edsal",
                "Edwards",
                "EICO",
                "Electrix",
                "Elite Products",
                "Elmer's",
                "Elvex",
                "Emerson",
                "Enduro",
                "Energizer",
                "Enerpac",
                "Enertrols",
                "Enidine",
                "Enshu",
                "Entegris",
                "Ergotron",
                "Erickson",
                "ERICO",
                "Erie",
                "Eurotherm",
                "Everbilt",
                "Evolution",
                "EXAIR",
                "Extron",
                "Factory 21",
                "Fadal",
                "Fagor",
                "Fairchild",
                "Falk",
                "FANUC",
                "Farmall",
                "Fasco",
                "FastCap",
                "Fastenal",
                "Federal-Mogul",
                "Federal Signal",
                "Fellowes",
                "Fenner Drives",
                "Festo",
                "Fike",
                "Finder",
                "Fireye",
                "First Aid Only",
                "First Alert",
                "Fisher",
                "Florence",
                "Flowserve",
                "FLT",
                "FLUID FILM",
                "FMC",
                "Folgers",
                "Ford",
                "Foxboro",
                "FPE",
                "Freeway",
                "Frieling",
                "Frigidaire",
                "FSP",
                "FSQ",
                "Fuji",
                "Fujitsu",
                "Fuller Brush",
                "Furnas",
                "FYH",
                "G.W. Lisk",
                "Galaxy",
                "Gardner Bender",
                "Gardner Denver",
                "Garlock",
                "Garmin",
                "Gates",
                "Gatorade",
                "GBC",
                "GC Electronics",
                "GE",
                "Geberit",
                "GE Fanuc",
                "Gefran",
                "Gemco",
                "Gemini",
                "Gems",
                "Gemu",
                "General Cable",
                "General Motors",
                "Genesis",
                "Genie",
                "Genpak",
                "Genuine Joe",
                "Georgia-Pacific",
                "GHS",
                "Giddings & Lewis",
                "Glenair",
                "GLI",
                "Global Industrial",
                "GMC",
                "GMN",
                "Goodman",
                "Goodyear",
                "Gould Shawmut",
                "Grabber",
                "Graco",
                "Grainger",
                "Graphic Controls",
                "Grayhill",
                "Greenlee",
                "Groen",
                "Grove Gear",
                "Gulf",
                "Haas",
                "Hach",
                "Hallman",
                "Hamilton",
                "Hammer",
                "Hammond",
                "Hampton",
                "Hanna",
                "Hantek",
                "Hardinge",
                "Harris",
                "HARTING",
                "Hatco",
                "Hayward",
                "HEIDENHAIN",
                "Heim",
                "Heinemann",
                "HellermannTyton",
                "Helwig Carbon",
                "Hertel",
                "HFH",
                "HIC",
                "Hillman",
                "Hilti",
                "Hitachi",
                "Hobart",
                "Hodgman",
                "Hoffman",
                "Hoffmann",
                "HOHNER",
                "Homelite",
                "Honda",
                "Honeywell",
                "Hoover",
                "HP",
                "Hubbell",
                "Hub City",
                "Hughes",
                "Hummer",
                "Humphrey",
                "Husky",
                "Husqvarna",
                "Hustler",
                "Hyatt",
                "IBM",
                "Icom",
                "Ideal",
                "IDEC",
                "Ignite",
                "Ikegai",
                "Ikegami",
                "Indramat",
                "INDUMAR",
                "Ingersoll Rand",
                "Inogen",
                "INSIZE",
                "Instant Power Professional",
                "Intel",
                "Intermec",
                "International Rectifier",
                "Intersil",
                "IPTCI",
                "iSK",
                "ITE",
                "ITT",
                "J.W. Speaker",
                "Jacobs",
                "Jacuzzi",
                "JAF",
                "Jaguar Plastics",
                "Jamesbury",
                "Japan",
                "Jason",
                "Jason Industrial",
                "JBS",
                "JCB",
                "Jeremywell",
                "Jergens",
                "JIB",
                "JM Clipper",
                "John Deere",
                "Johnson",
                "Johnson & Johnson",
                "Johnson Controls",
                "Joslyn Clark",
                "Joy",
                "Justrite",
                "Kashi",
                "Kawasaki",
                "Kaydon",
                "KBC",
                "Keeper",
                "KENDA",
                "Kendall",
                "Key",
                "KEYENCE",
                "Keystone",
                "Kilian",
                "Killark",
                "Kirkland Signature",
                "Kitamura",
                "KNIPEX",
                "Kobe",
                "Koblenz",
                "Kohler",
                "Konica Minolta",
                "Koyo Electronics",
                "Kromschroder",
                "Ksk",
                "KSM",
                "Kubota",
                "Kuraki",
                "Kurt J Lesker",
                "KYK",
                "Kyocera",
                "L&S",
                "Lambda",
                "Lamont",
                "Lam Research",
                "Lee",
                "Leica",
                "LENNOX",
                "Lenox",
                "Leuze",
                "Leviton",
                "LG",
                "Lightolier",
                "Lincoln",
                "Lind",
                "Linde",
                "LINEMASTER",
                "Link-Belt",
                "Loc-Line",
                "Loctite",
                "Lovato",
                "Lovejoy",
                "LPS",
                "Lucent",
                "Lumistick",
                "Mac Tools",
                "Mag-Lite",
                "Mag-Mate",
                "Magnaloy",
                "Magnavox",
                "Magnecraft",
                "Magnetek",
                "Magnolia",
                "Magnum",
                "Makino",
                "Makita",
                "Marathon",
                "Marathon Electric",
                "Marco",
                "Marjack",
                "Marposs",
                "Mars",
                "Marsh",
                "Marshalltown",
                "Marsh Bellofram",
                "Marson",
                "Martin",
                "Mary Kay",
                "MASKA",
                "Mason",
                "Master",
                "Master Lock",
                "Matco Tools",
                "Materro",
                "Mathews",
                "Mathews Wire",
                "Matsuura",
                "Maxam",
                "Maxon",
                "Max Professional",
                "Maxwell House",
                "Maytag",
                "Mazak",
                "MB",
                "MBS",
                "McGill",
                "MCR Safety",
                "MDC",
                "MEAN WELL",
                "Measurex",
                "Medline",
                "Melles Griot",
                "Meltric",
                "Mencom",
                "Merit",
                "Mersen",
                "METTLER",
                "Mettler Toledo",
                "MGM",
                "Midmark",
                "Mikasa",
                "Milacron",
                "Miljoco",
                "Miller",
                "Milwaukee",
                "Minolta",
                "Minuteman",
                "Mirka",
                "Mitsubishi",
                "Mitsubishi Electric",
                "Mitutoyo",
                "Moeller",
                "Molex",
                "Monarch Specialties",
                "MONTALE",
                "MOOG",
                "Mopar",
                "Mori Seiki",
                "Morris",
                "Morse",
                "Motorola",
                "MSA",
                "Mst",
                "MTD",
                "MTI",
                "Multicomp",
                "Murray",
                "Murrelektronik",
                "Mustang",
                "MVP",
                "Nachi",
                "NAPA",
                "National",
                "National Instruments",
                "NBK",
                "NBR",
                "NC",
                "NEC",
                "New Era",
                "New Holland",
                "Nexera",
                "Nexus",
                "NGK",
                "NHBB",
                "Niagara",
                "NICE",
                "Nichicon",
                "Nikken",
                "Nikon",
                "Niles",
                "Nippon",
                "Nippon Bearing",
                "NKE",
                "NMB",
                "Noga",
                "Nordson",
                "Norgren",
                "Norma",
                "Norpro",
                "North",
                "North Safety",
                "Norton",
                "NOSHOK",
                "Novellus",
                "NTN",
                "Nuline",
                "Numatics",
                "OBARA",
                "Oberdorfer",
                "OccuNomix",
                "OCSparts",
                "Ohaus",
                "Ohmite",
                "Okuma",
                "Oliver",
                "OMEGA",
                "Omron",
                "OPTIBELT",
                "Optima",
                "Opto 22",
                "Orange",
                "Orbit",
                "Oregon",
                "ORGAN",
                "Oriental Motor",
                "Orion Fans",
                "ORS",
                "Osborn",
                "OSG",
                "OSG Corporation",
                "OTC",
                "own",
                "O-Z/Gedney",
                "P&H",
                "Pacific",
                "Pall",
                "Palmer",
                "Panasonic",
                "Panduit",
                "Parker",
                "Parlec",
                "Partlow",
                "Pass & Seymour",
                "PATLITE",
                "PECO",
                "PEER",
                "Peerless",
                "Pegasus",
                "Pelouze",
                "Pennzoil",
                "Pentek",
                "Pepperl",
                "PerkinElmer",
                "Permatex",
                "Philips",
                "Piab",
                "Pilz",
                "Pinnacle",
                "Pioneer",
                "Plymouth",
                "Pontiac",
                "PORTER-CABLE",
                "Potter & Brumfield Relays",
                "Powerbuilt",
                "Powermatic",
                "Power Probe",
                "Powers",
                "Precision",
                "PTI",
                "Quantum",
                "Quartet",
                "Quincy",
                "R&M",
                "RAB Lighting",
                "RACO",
                "Radnor",
                "Ragalta",
                "Ranco",
                "Randall",
                "Ranger",
                "Raychem",
                "Raymond",
                "RBC",
                "RBI",
                "RCA",
                "Red Devil",
                "Red Jacket",
                "Red Line",
                "Red Lion Controls",
                "Reese",
                "Reeves",
                "Regal",
                "Regency",
                "Regent",
                "Reject",
                "Reliance",
                "Reliance Electric",
                "Relton",
                "Renegade",
                "Renold",
                "Repco",
                "Rexnord",
                "Rexroth",
                "Rhino",
                "RHP",
                "Rice Lake",
                "Ricoh",
                "RIDGID",
                "Ritec",
                "Rittal",
                "Ritter",
                "Riv",
                "Roberts",
                "Robertshaw",
                "Robin",
                "Robohand",
                "Rockwell",
                "Rockwood",
                "ROHN",
                "Rollway",
                "Ronstan",
                "Rosemount",
                "Rotary",
                "Royal",
                "RPM",
                "RTI",
                "Rubbermaid",
                "Ruland",
                "Safco",
                "Samsung",
                "Sandvik Coromant",
                "SANYO DENKI",
                "SATA",
                "Saunders",
                "Schatz",
                "Schlage",
                "Schmidt",
                "Schneider",
                "Schneider Electric",
                "Schrader Bellows",
                "Schroff",
                "Schumacher",
                "Scotch",
                "Scott Safety",
                "Seagate",
                "Sea Striker",
                "Seaward",
                "SECO",
                "Select",
                "Sellstrom",
                "SEMIKRON",
                "SENCO",
                "Sennheiser",
                "Sensata Technologies",
                "Setra",
                "SEW-EURODRIVE",
                "SGI",
                "Shafer",
                "Shark",
                "Sharp",
                "Shelby",
                "Shell",
                "Shimadzu",
                "Shindengen",
                "Showa",
                "Siemens",
                "Sigma",
                "Signode",
                "SKF",
                "SKYSEA",
                "Slime",
                "Sloan",
                "SMA",
                "SMC",
                "Smith",
                "SMT",
                "Snap-on",
                "SNR",
                "Sodick",
                "Sony",
                "Southworth",
                "Spears",
                "Spectra Precision",
                "Spectrum",
                "SPEEDAIRE",
                "Speed Control Industries",
                "Spherco",
                "Spicer",
                "Spirax",
                "Sporlan",
                "Spraymation",
                "Square D",
                "Sqwincher",
                "SST",
                "Stabilus",
                "Standard",
                "Stanley",
                "Staples",
                "Star",
                "Starbucks",
                "Starrett",
                "STAUFF",
                "Stearns",
                "Stens",
                "Sterling",
                "Steyr Motors",
                "STI",
                "STIHL",
                "Subaru",
                "Sullair",
                "Suncast",
                "Sunnen",
                "SUPCO",
                "Superior",
                "Super Lube",
                "SureFit",
                "Swagelok",
                "Swift",
                "Swift First Aid",
                "SYLVANIA",
                "Symbol",
                "TAKISAWA",
                "Tamura",
                "Target",
                "Tatung",
                "Taylor",
                "TB Wood's",
                "TCM",
                "TDK",
                "TE Connectivity",
                "Tecumseh",
                "Tektronix",
                "TEL",
                "Telemecanique",
                "Tennant",
                "Tennsco",
                "Terex",
                "Terumo",
                "Testrite",
                "Texas Instruments",
                "The Ergo Office",
                "The Home Depot",
                "Thermoid",
                "THK",
                "Thomas & Betts",
                "Thomson",
                "Timken",
                "Titan",
                "Tokimec",
                "TopWorx",
                "Toray",
                "Tork",
                "Toro",
                "Toshiba",
                "Toyota",
                "TPI",
                "TP-LINK",
                "Tr",
                "Trademark Global",
                "Trane",
                "Trerice",
                "Triangle",
                "Trico",
                "Trimble",
                "Tripp Lite",
                "Triton",
                "Trojan",
                "TRUE COMPOSITES",
                "Tru-Maxx",
                "TRW",
                "Tsubaki",
                "Turck",
                "TYCO",
                "Tygon",
                "Tyson",
                "U.S. Solid",
                "U-Line",
                "Ulvac",
                "Unbranded",
                "Ungar",
                "Unico",
                "Unitech",
                "United Electric Controls",
                "Update International",
                "UPG",
                "URB",
                "US Cargo Control",
                "Valenite",
                "Valley Forge",
                "Value Collection",
                "Van Dorn",
                "VARGUS",
                "Varian",
                "VAT",
                "Veris",
                "Verizon",
                "Versa",
                "Vestil",
                "VEVOR",
                "Vibco",
                "Vickers",
                "Vicor",
                "VICTOR",
                "Videojet",
                "Viking",
                "Vision Metalizers",
                "Volkswagen",
                "Volvo",
                "Vulcan",
                "WAGNER",
                "Wakefield-Vette",
                "Walbro",
                "Warner Electric",
                "Watlow",
                "Watts",
                "Weatherhead",
                "Weidm\u00fcller",
                "Weil",
                "Welch Allyn",
                "Weller",
                "Wells",
                "Wera",
                "Western",
                "Western Enterprises",
                "Westinghouse",
                "Westward",
                "WHEELER",
                "White-Rodgers",
                "Whitey",
                "Wiegmann",
                "Wieland Electric",
                "Wilkerson",
                "Williams",
                "Wilmar",
                "Wilson Jones",
                "WINSMITH",
                "Wipe New",
                "WireCrafters",
                "Wolff",
                "Wolverine",
                "Wood Designs",
                "Woodhead",
                "Woods",
                "World Dryer",
                "Wright",
                "Wyse",
                "Xcelite",
                "Xerox",
                "Xilinx",
                "Xycom",
                "Xyron",
                "Yale",
                "Yamaha",
                "Yankee Candle",
                "Yaskawa",
                "YKK",
                "Yokogawa",
                "YORK",
                "Zama",
                "Zebra",
                "Zinsco",
                "ZKL",
                "ZNL",
                "Zurn",
                "ZVL"
            ]
        },
        {
            "name": "Model",
            "required": false,
            "mode": "FREE_TEXT",
            "data_type": "STRING",
            "cardinality": "SINGLE",
            "for_variations": true,
            "values": []
        },
        {
            "name": "MPN",
            "required": false,
            "mode": "FREE_TEXT",
            "data_type": "STRING",
            "cardinality": "SINGLE",
            "for_variations": true,
            "values": []
        },
        {
            "name": "Expiration Date",
            "required": false,
            "mode": "FREE_TEXT",
            "data_type": "STRING",
            "cardinality": "SINGLE",
            "for_variations": false,
            "values": []
        },
        {
            "name": "California Prop 65 Warning",
            "required": false,
            "mode": "FREE_TEXT",
            "data_type": "STRING",
            "cardinality": "SINGLE",
            "for_variations": false,
            "values": []
        },
        {
            "name": "Country of Origin",
            "required": false,
            "mode": "SELECTION_ONLY",
            "data_type": "STRING",
            "cardinality": "SINGLE",
            "for_variations": false,
            "values": [
                "Afghanistan",
                "Albania",
                "Algeria",
                "Andorra",
                "Angola",
                "Anguilla",
                "Antigua and Barbuda",
                "Argentina",
                "Armenia",
                "Aruba",
                "Australia",
                "Austria",
                "Azerbaijan",
                "Bahamas",
                "Bahrain",
                "Bangladesh",
                "Barbados",
                "Belarus",
                "Belgium",
                "Belize",
                "Benin",
                "Bermuda",
                "Bhutan",
                "Bolivia",
                "Bosnia and Herzegovina",
                "Botswana",
                "Brazil",
                "British Indian Ocean Territory",
                "Brunei Darussalam",
                "Bulgaria",
                "Burkina Faso",
                "Burundi",
                "Cambodia",
                "Cameroon",
                "Canada",
                "Cape Verde",
                "Cayman Islands",
                "Central African Republic",
                "Chad",
                "Chile",
                "China",
                "Cocos (Keeling) Islands",
                "Colombia",
                "Comoros",
                "Cook Islands",
                "Costa Rica",
                "Croatia",
                "Cyprus",
                "Denmark",
                "Djibouti",
                "Dominica",
                "Dominican Republic",
                "Ecuador",
                "Egypt",
                "El Salvador",
                "Equatorial Guinea",
                "Eritrea",
                "Estonia",
                "Ethiopia",
                "Falkland Islands",
                "Faroe Islands",
                "Fiji",
                "Finland",
                "France",
                "French Guiana",
                "French Polynesia Includes Tahiti",
                "Gabon",
                "Gambia",
                "Georgia",
                "Germany",
                "Ghana",
                "Gibraltar",
                "Greece",
                "Greenland",
                "Grenada",
                "Guadeloupe",
                "Guam",
                "Guatemala",
                "Guernsey",
                "Guinea",
                "Guinea-Bissau",
                "Guyana",
                "Haiti",
                "Heard Island and Mcdonald Islands",
                "Honduras",
                "Hong Kong",
                "Hungary",
                "Iceland",
                "India",
                "Indonesia",
                "Iraq",
                "Ireland",
                "Israel",
                "Italy",
                "Jamaica",
                "Japan",
                "Jersey",
                "Jordan",
                "Kazakhstan",
                "Kenya",
                "Kiribati",
                "Kuwait",
                "Kyrgyzstan",
                "Lao People's Democratic Republic",
                "Latvia",
                "Lebanon",
                "Lesotho",
                "Liberia",
                "Liechtenstein",
                "Lithuania",
                "Luxembourg",
                "North Macedonia",
                "Madagascar",
                "Malawi",
                "Malaysia",
                "Maldives",
                "Mali",
                "Malta",
                "Marshall Islands",
                "Martinique",
                "Mauritania",
                "Mauritius",
                "Mayotte",
                "Mexico",
                "Micronesia, Federated States of",
                "Moldova, Republic of",
                "Monaco",
                "Mongolia",
                "Montenegro",
                "Montserrat",
                "Morocco",
                "Mozambique",
                "Namibia",
                "Nauru",
                "Nepal",
                "Netherlands",
                "New Caledonia",
                "New Zealand",
                "Nicaragua",
                "Niger",
                "Nigeria",
                "Niue",
                "Norfolk Island",
                "Northern Mariana Islands",
                "Norway",
                "Oman",
                "Pakistan",
                "Palau",
                "Panama",
                "Papua New Guinea",
                "Paraguay",
                "Peru",
                "Philippines",
                "Poland",
                "Portugal",
                "Puerto Rico",
                "Qatar",
                "Reunion",
                "Romania",
                "Russian Federation",
                "Rwanda",
                "Saint Helena",
                "Saint Kitts and Nevis",
                "Saint Lucia",
                "Saint Pierre and Miquelon",
                "Saint Vincent and the Grenadines",
                "Samoa",
                "San Marino",
                "Sao Tome and Principe",
                "Saudi Arabia",
                "Senegal",
                "Serbia",
                "Seychelles",
                "Sierra Leone",
                "Singapore",
                "Slovakia",
                "Slovenia",
                "Solomon Islands",
                "Somalia",
                "South Africa",
                "South Georgia and the South Sandwich Islands",
                "Spain",
                "Sri Lanka",
                "Suriname",
                "Svalbard and Jan Mayen",
                "Eswatini",
                "Sweden",
                "Switzerland",
                "Taiwan",
                "Tajikistan",
                "Tanzania, United Republic of",
                "Thailand",
                "Togo",
                "Tokelau",
                "Tonga",
                "Trinidad and Tobago",
                "Tunisia",
                "Turkmenistan",
                "Turks and Caicos Islands",
                "Tuvalu",
                "Uganda",
                "Ukraine",
                "United Arab Emirates",
                "United Kingdom",
                "United States",
                "Uruguay",
                "Uzbekistan",
                "Vanuatu",
                "Venezuela",
                "Vietnam",
                "Wallis and Futuna",
                "Yemen",
                "Zambia",
                "Zimbabwe",
                "British Virgin Islands",
                "Canary Islands",
                "Christmas Islands",
                "Congo, Republic of the",
                "Congo, The Democratic Republic of the",
                "C\u00f4te d'Ivoire",
                "Cuba",
                "Curacao",
                "Czech Republic",
                "French Southern Territories and Antartic Lands",
                "Gaza Strip",
                "Iran, Islamic Republic of",
                "Kosovo",
                "Libya",
                "Macau",
                "Madeira Island",
                "Myanmar / Burma",
                "North Korea (Democratic People's Republic of Korea)",
                "Saint Barth\u00e9lemy",
                "Saint-Martin",
                "Sint Eustatius",
                "Sint Maarten",
                "South Korea (Republic of Korea)",
                "Sudan",
                "Syria",
                "Tristan da Cunha",
                "T\u00fcrkiye",
                "Vatican City",
                "Virgin Islands",
                "West Bank"
            ]
        },
        {
            "name": "Unit Quantity",
            "required": false,
            "mode": "FREE_TEXT",
            "data_type": "STRING",
            "cardinality": "SINGLE",
            "for_variations": false,
            "values": []
        },
        {
            "name": "Unit Type",
            "required": false,
            "mode": "SELECTION_ONLY",
            "data_type": "STRING",
            "cardinality": "SINGLE",
            "for_variations": false,
            "values": [
                "Unit",
                "oz",
                "lb",
                "fl oz",
                "gal",
                "ft",
                "ft\u00b2",
                "ft\u00b3"
            ]
        }
    ]
}
