{
    "item_id": "127389878212",
    "title": "ASR Outdoor Rechargeable Adjustable 2250 Lumen LED Headlamp Four-Stage Switch",
    "category_id": "106984",
    "category_path": "Sporting Goods|Camping & Hiking|Flashlights, Lanterns & Lights|Headlamps",
    "aspects": {
        "Brand": "ASR Outdoor",
        "Battery Technology": "Lithium-ion",
        "California Prop 65 Warning": "CALIFORNIA WARNING: This product can expose you to chemicals including bisphenol_a_(bpa), which is known to the State of California to cause cancer, birth defects or other reproductive harm. For more information, go to: www.P65Warnings.ca.gov",
        "Color": "Black",
        "Country of Origin": "China",
        "Features": "4-STAGE SWITCH - The four-stage switch with",
        "Item Height": "5 in",
        "Item Length": "10.5 in",
        "Item Weight": "0.68 lb",
        "Item Width": "7 in",
        "Lighting Technology": "LED",
        "Lumens": "2250 lm",
        "MPN": "RLEDHL",
        "Material": "Plastic",
        "Model": "RLEDHL",
        "Power Source": "Battery",
        "Size": "Medium",
        "Type": "Headlamp",
        "UPC": "060886618522",
        "Unit Quantity": "1",
        "Unit Type": "Unit"
    },
    "condition": "New",
    "is_group": false,
    "variation_count": 0,
    "status": "OK"
}
