{
    "item_id": "127389838864",
    "title": "DIY Craft Self Healing Cutting Mat Double Sided Hobby Tool (2 Sizes and Colors)",
    "category_id": "16507",
    "category_path": "Crafts|Stamping & Embossing|Tools & Equipment",
    "aspects": {
        "Color": "Green",
        "Size": "9\" x 12\"",
        "Brand": "ToolTreaux",
        "Model": "UTSCM",
        "MPN": "UTSCM",
        "Country/Region of Manufacture": "Taiwan",
        "Country of Origin": "China"
    },
    "condition": "New",
    "is_group": true,
    "variation_count": 4,
    "status": "OK"
}
