{
    "item_id": "127389932527",
    "title": "Fresh Mint Dental Floss for Teeth and Gum Oral Care Remove Food and Plaque 12pk",
    "category_id": "159758",
    "category_path": "Health & Beauty|Oral Care|Dental Floss & Flossers",
    "aspects": {
        "Brand": "Home Essentials",
        "Type": "Dental Floss",
        "Color": "White",
        "Country of Origin": "China",
        "Department": "Unisex Adults",
        "Features": "DENTAL FLOSS: An oral health essential, dental",
        "MPN": "HEFMDT12PK",
        "Manufacturer Warranty": "Limited Manufacturer Direct",
        "Model": "HEFMDT12PK",
        "Size": "Small",
        "UPC": "885189918618",
        "Unit Quantity": "1",
        "Unit Type": "Unit"
    },
    "condition": "New",
    "is_group": false,
    "variation_count": 0,
    "status": "OK"
}
