{
    "item_id": "127389768427",
    "title": "Universal Tool High Speed Steel Step Drill Bits Locking Hex Shank Assorted - 3pc",
    "category_id": "50382",
    "category_path": "Home & Garden|Tools & Workshop Equipment|Power Tool & Air Tool Accessories|Drill Bits",
    "aspects": {
        "Country of Origin": "China",
        "Brand": "Universal Tool",
        "Type": "Drill Bit",
        "Package Quantity": "1",
        "Material": "Steel",
        "Model": "UTSDBS3PC",
        "MPN": "UTSDBS3PC",
        "Color": "Gold",
        "Item Length": "6.000",
        "Item Width": "3.500",
        "Item Weight": "0.3000",
        "Item Height": "0.500",
        "California Prop 65 Warning": "WARNING: This product may contain chemicals known to the State of California to cause cancer, birth defects or other reproductive harm",
        "Size": "Small",
        "UPC": "060886768944"
    },
    "condition": "New",
    "is_group": false,
    "variation_count": 0,
    "status": "OK"
}
