{
    "item_id": "235399090909",
    "title": "Cord Made with Kevlar Survival Paracord Rope 200lbs Strength (Various Lengths)",
    "category_id": "181413",
    "category_path": "Sporting Goods|Camping & Hiking|Outdoor Survival Gear|Paracord & Paracord Supplies",
    "aspects": {
        "Color": "Blue",
        "Size": "1000ft",
        "Brand": "ASR Tactical",
        "Type": "Paracord",
        "California Prop 65 Warning": "CALIFORNIA WARNING: This product can expose you to chemicals including bisphenol_a_(bpa), which is known to the State of California to cause cancer, birth defects or other reproductive harm. For more information, go to: www.P65Warnings.ca.gov",
        "Country of Origin": "Japan",
        "Features": "Lightweight",
        "Item Length": "12 in",
        "Item Weight": "1 lb",
        "Item Width": "6 in",
        "MPN": "ASRKEV013-408",
        "Material": "Kevlar",
        "Model": "ASRKEV013-408",
        "Number in Pack": "1",
        "Number of Strands": "3",
        "Suitable For": "Backpacking, Camping, Hiking",
        "Tensile Strength": "200 lb",
        "Thickness": "0.1 in",
        "Unit Quantity": "1",
        "Unit Type": "Unit"
    },
    "condition": "New",
    "is_group": true,
    "variation_count": 10,
    "status": "OK"
}
