{
    "item_id": "236345069168",
    "title": "SE 8372SH Stone Hammer, 10\"",
    "category_id": "20763",
    "category_path": "Home & Garden|Tools & Workshop Equipment|Hand Tools|Hammers & Mallets",
    "aspects": {
        "Brand": "SE",
        "Type": "Stonemason's Mallet",
        "Color": "Black",
        "Country of Origin": "China",
        "Head/Face Material": "Steel",
        "Item Height": "4 in",
        "Item Length": "10 in",
        "Item Weight": "1.98 lb",
        "Item Width": "4 in",
        "Manufacturer Warranty": "Limited Manufacturer Direct",
        "Model": "8372SH",
        "Personalize": "No",
        "Unit Quantity": "1",
        "Unit Type": "Unit"
    },
    "condition": "New",
    "is_group": false,
    "variation_count": 0,
    "status": "OK"
}
