{
    "item_id": "364855706606",
    "title": "ASR Outdoor 22pc Backpack Kit, Beach Combing Metal Detector Accessories Set",
    "category_id": "163824",
    "category_path": "Business & Industrial|Test, Measurement & Inspection|Test Meters & Detectors|Metal Detector Accessories",
    "aspects": {
        "Brand": "ASR Outdoor",
        "MPN": "ASRBDKIT22PC",
        "Color": "Green",
        "Country of Origin": "China",
        "Featured Refinements": "Gold Panning Kit",
        "Model": "ASRBDKIT22PC",
        "Size": "Large",
        "Type": "Accessory Bundle",
        "UPC": "810058486196",
        "Unit Quantity": "1",
        "Unit Type": "Unit"
    },
    "condition": "New",
    "is_group": false,
    "variation_count": 0,
    "status": "OK"
}
