{
    "item_id": "364909134364",
    "title": "Beille Kitchen Utensils High Heat Resistance Baking Cooking Tools (Many Styles)",
    "category_id": "20649",
    "category_path": "Home & Garden|Kitchen, Dining & Bar|Kitchen Tools & Gadgets|Cooking Utensils",
    "aspects": {
        "Style": "Can Opener",
        "Brand": "Beille",
        "Color": "Beige",
        "Country of Origin": "China",
        "Country/Region of Manufacture": "China",
        "Features": "Heat Resistant",
        "MPN": "BLECKTLS",
        "Material": "Wheat Straw",
        "Number of Items in Set": "3",
        "Pattern": "Solid",
        "Personalize": "No",
        "Type": "Kitchen Utensils",
        "Unit Quantity": "1",
        "Unit Type": "Unit"
    },
    "condition": "New",
    "is_group": true,
    "variation_count": 15,
    "status": "OK"
}
