{
    "item_id": "365879908034",
    "title": "Beille Silicone Baby Feeding Essentials Ages One and Up (Many Styles and Colors)",
    "category_id": "117386",
    "category_path": "Baby|Feeding|Cups, Dishes & Utensils|Feeding Sets",
    "aspects": {
        "Color": "Blue",
        "Style": "2pc Bowl Set",
        "Brand": "Beille",
        "California Prop 65 Warning": "CALIFORNIA WARNING: This product can expose you to chemicals including bisphenol_a_(bpa), which is known to the State of California to cause cancer, birth defects or other reproductive harm. For more information, go to: www.P65Warnings.ca.gov",
        "Country of Origin": "China",
        "Country/Region of Manufacture": "China",
        "Features": "Dishwasher Safe",
        "Type": "Mixed Set",
        "Unit Quantity": "1",
        "Unit Type": "Unit"
    },
    "condition": "New",
    "is_group": true,
    "variation_count": 41,
    "status": "OK"
}
