{
    "item_id": "365879935296",
    "title": "ASR Federal Disposable Latex Glove Holder Duty Belt Hook Loop Closure EMT",
    "category_id": "53294",
    "category_path": "Business & Industrial|Facility Maintenance & Safety|Public Safety Staff Equipment|Police & Turnout Gear|Other Police & Turnout Gear",
    "aspects": {
        "Brand": "ASR Federal",
        "Color": "Black",
        "Country of Origin": "United States",
        "MPN": "ASRTDGHLD1",
        "Model": "ASRTDGHLD1",
        "Size": "4.5 in x 4 in",
        "Thickness": "0.25 in",
        "Type": "Gloves",
        "UPC": "810058480293",
        "Unit Quantity": "1",
        "Unit Type": "Unit"
    },
    "condition": "New",
    "is_group": false,
    "variation_count": 0,
    "status": "OK"
}
