{
    "item_id": "365879832388",
    "title": "3.5 Inch Tailoring Straight Sharp Tip Scissors Stainless Steel Stork - Gold",
    "category_id": "28171",
    "category_path": "Crafts|Sewing|Cutting Tools|Dressmaker's Scissors & Shears",
    "aspects": {
        "Country of Origin": "China",
        "Brand": "Universal Hobby",
        "Type": "Sewing Scissors",
        "Features": "STORK STYLE CRAFTING SCISSORS - These super sharp",
        "MPN": "SSSS-1-900-G",
        "California Prop 65 Warning": "WARNING: This product can expose you to chemicals including bisphenol_a_(bpa), which is known to the State of California to cause cancer, birth defects or other reproductive harm. For more information, go to: www.P65Warnings.ca.gov",
        "Color": "Gold",
        "Size": "3.5 Inch",
        "UPC": "810058485304"
    },
    "condition": "New",
    "is_group": false,
    "variation_count": 0,
    "status": "OK"
}
