{
    "item_id": "256446183297",
    "title": "GEAR AID Tenacious Tape Reflective, Jackets, Outdoor Gear, 3\" x 20\", Silver",
    "category_id": "36120",
    "category_path": "Sporting Goods|Camping & Hiking|Tents & Canopies|Tent & Canopy Accessories",
    "aspects": {
        "Style": "1 Pack",
        "Brand": "Gear Aid",
        "Type": "standard",
        "Size": "3 x 20 inches",
        "Color": "Reflective",
        "Item Height": "12.000",
        "MPN": "10785",
        "Item Length": "4.000",
        "Item Width": "0.500",
        "Country of Origin": "United States"
    },
    "condition": "New",
    "is_group": true,
    "variation_count": 2,
    "status": "OK"
}
