{
    "item_id": "256446183545",
    "title": "GEAR AID Elastic Shock Cord for Tent Poles and Jackets, 84\", Black",
    "category_id": "36120",
    "category_path": "Sporting Goods|Camping & Hiking|Tents & Canopies|Tent & Canopy Accessories",
    "aspects": {
        "Brand": "GEAR AID",
        "Type": "standard",
        "Size": "80\"",
        "Color": "Black",
        "Item Height": "0.500",
        "Features": "Replace shock cords in tent poles, jackets and",
        "MPN": "80650",
        "Item Length": "4.000",
        "Item Width": "2.750",
        "Country of Origin": "China",
        "UPC": "021563806502"
    },
    "condition": "New",
    "is_group": false,
    "variation_count": 0,
    "status": "OK"
}
