{
    "item_id": "256446183294",
    "title": "Gear Aid Revivex Durable Water Proofing Pro Cleaner Combo Kit 10oz",
    "category_id": "310",
    "category_path": "Sporting Goods|Other Sporting Goods",
    "aspects": {
        "Brand": "Gear Aid",
        "Size": "Standard",
        "Color": "Multi-Color",
        "Model": "MGARWP-10SCMB12CN",
        "MPN": "MGARWP-10SCMB12CN",
        "Country of Origin": "United States",
        "California Prop 65 Warning": "This product may contain chemicals known to the State of California to cause cancer, birth defects or other reproductive harm",
        "UPC": "181624308168"
    },
    "condition": "New",
    "is_group": false,
    "variation_count": 0,
    "status": "OK"
}
