{
    "item_id": "256462817220",
    "title": "ASR Outdoor Riffled Rubber Sluice Box Matting. 27\" x 10\"",
    "category_id": "26261",
    "category_path": "Business & Industrial|Other Business & Industrial",
    "aspects": {
        "Country of Origin": "China",
        "Brand": "ASR Outdoor",
        "MPN": "TRSBM",
        "Model": "TRSBM",
        "Color": "Green",
        "Size": "3'",
        "UPC": "706569093100"
    },
    "condition": "New",
    "is_group": false,
    "variation_count": 0,
    "status": "OK"
}
