{
    "item_id": "256510048028",
    "title": "Universal Tool Acid Brush Set 6 Inch Metal Handle for Acid Glue Paste 12pc Set",
    "category_id": "183161",
    "category_path": "Crafts|Home Arts & Crafts|Woodworking|Other Woodworking Supplies",
    "aspects": {
        "Country of Origin": "China",
        "Brand": "Universal Tool",
        "Type": "standard",
        "MPN": "UHABS12",
        "California Prop 65 Warning": "This product may contain chemicals known to the State of California to cause cancer, birth defects or other reproductive harm",
        "Color": "Silver",
        "Size": "6\"",
        "UPC": "060886617273"
    },
    "condition": "New",
    "is_group": false,
    "variation_count": 0,
    "status": "OK"
}
